.gitignore
LICENSE
README.rst
setup.cfg
setup.py
xdh/__init__.py
xdh/_config.py
xdh/config.py
xdh_config.egg-info/PKG-INFO
xdh_config.egg-info/SOURCES.txt
xdh_config.egg-info/dependency_links.txt
xdh_config.egg-info/top_level.txt